Offset_Subtraction/__init__.py
Offset_Subtraction/_version.py
Offset_Subtraction/subtraction.py
Offset_Subtraction-0.0.5.dist-info/LICENSE
Offset_Subtraction-0.0.5.dist-info/METADATA
Offset_Subtraction-0.0.5.dist-info/WHEEL
Offset_Subtraction-0.0.5.dist-info/entry_points.txt
Offset_Subtraction-0.0.5.dist-info/top_level.txt
Offset_Subtraction-0.0.5.dist-info/RECORD
